pyalpaca/__init__.py
pyalpaca-0.0.1.dev0.dist-info/METADATA
pyalpaca-0.0.1.dev0.dist-info/WHEEL
pyalpaca-0.0.1.dev0.dist-info/top_level.txt
pyalpaca-0.0.1.dev0.dist-info/RECORD
